docktree/__init__.py
docktree/__main__.py
docktree-0.3.1.dist-info/DESCRIPTION.rst
docktree-0.3.1.dist-info/METADATA
docktree-0.3.1.dist-info/RECORD
docktree-0.3.1.dist-info/WHEEL
docktree-0.3.1.dist-info/entry_points.txt
docktree-0.3.1.dist-info/metadata.json
docktree-0.3.1.dist-info/top_level.txt
