Metadata-Version: 2.0
Name: docktree
Version: 0.3.1
Summary: Display the local Docker image layers as a tree
Home-page: https://github.com/cmihai/docktree
Author: Mihai Ciumeică
Author-email: UNKNOWN
License: MIT
Platform: UNKNOWN
Classifier: Development Status :: 4 - Beta
Classifier: Environment :: Console
Classifier: Intended Audience :: System Administrators
Classifier: Operating System :: POSIX :: Linux
Classifier: License :: OSI Approved :: MIT License
Classifier: Programming Language :: Python
Classifier: Programming Language :: Python :: 2.7
Classifier: Programming Language :: Python :: 3.2
Classifier: Programming Language :: Python :: 3.3
Classifier: Programming Language :: Python :: 3.4 
Requires-Dist: docker-py (>=1.5.0)
